{
  "links": [
    {
      "target": "I4",
      "value": 226211,
      "source": "Y4"
    },
    {
      "target": "Z4",
      "value": 90653,
      "source": "A1"
    },
    {
      "target": "H4",
      "value": 40376,
      "source": "Y4"
    },
    {
      "target": "Z2",
      "value": 7268,
      "source": "H4"
    },
    {
      "target": "Y4",
      "value": 7051,
      "source": "Z4"
    },
    {
      "target": "G1",
      "value": 4781,
      "source": "Z1"
    },
    {
      "target": "I1",
      "value": 4009,
      "source": "G1"
    },
    {
      "target": "I2",
      "value": 3944,
      "source": "G2"
    },
    {
      "target": "Z4",
      "value": 3051,
      "source": "Z4"
    },
    {
      "target": "Y4",
      "value": 2748,
      "source": "P4"
    },
    {
      "target": "I7",
      "value": 2579,
      "source": "Y7"
    },
    {
      "target": "I6",
      "value": 2259,
      "source": "Y5"
    },
    {
      "target": "G2",
      "value": 2241,
      "source": "Z2"
    },
    {
      "target": "Z4",
      "value": 1708,
      "source": "T2"
    },
    {
      "target": "H4",
      "value": 1487,
      "source": "X2"
    },
    {
      "target": "Y1",
      "value": 1293,
      "source": "H4"
    },
    {
      "target": "Z4",
      "value": 1281,
      "source": "H4"
    },
    {
      "target": "G2",
      "value": 1264,
      "source": "Z1"
    },
    {
      "target": "G2",
      "value": 1235,
      "source": "Y1"
    },
    {
      "target": "Y5",
      "value": 1166,
      "source": "H4"
    },
    {
      "target": "V3",
      "value": 1075,
      "source": "A1"
    },
    {
      "target": "I4",
      "value": 828,
      "source": "I2"
    },
    {
      "target": "P4",
      "value": 620,
      "source": "H4"
    },
    {
      "target": "A1",
      "value": 479,
      "source": "V3"
    },
    {
      "target": "Y4",
      "value": 437,
      "source": "Y4"
    },
    {
      "target": "A1",
      "value": 429,
      "source": "A1"
    },
    {
      "target": "G1",
      "value": 429,
      "source": "Z4"
    },
    {
      "target": "I4",
      "value": 382,
      "source": "W2"
    },
    {
      "target": "G2",
      "value": 376,
      "source": "Z4"
    },
    {
      "target": "Z1",
      "value": 362,
      "source": "Z4"
    },
    {
      "target": "I5",
      "value": 344,
      "source": "G2"
    },
    {
      "target": "I4",
      "value": 286,
      "source": "I4"
    },
    {
      "target": "I8",
      "value": 266,
      "source": "G8"
    },
    {
      "target": "Y4",
      "value": 265,
      "source": "G4"
    },
    {
      "target": "G2",
      "value": 262,
      "source": "Y4"
    },
    {
      "target": "Z4",
      "value": 256,
      "source": "T4"
    },
    {
      "target": "A1",
      "value": 234,
      "source": "Z4"
    },
    {
      "target": "Z4",
      "value": 201,
      "source": "P4"
    },
    {
      "target": "Y4",
      "value": 185,
      "source": "H4"
    },
    {
      "target": "I4",
      "value": 183,
      "source": "X2"
    },
    {
      "target": "Z4",
      "value": 182,
      "source": "S2"
    },
    {
      "target": "G2",
      "value": 180,
      "source": "I4"
    },
    {
      "target": "I4",
      "value": 174,
      "source": "H4"
    },
    {
      "target": "I4",
      "value": 171,
      "source": "G2"
    },
    {
      "target": "G8",
      "value": 170,
      "source": "Z8"
    },
    {
      "target": "W2",
      "value": 162,
      "source": "H4"
    },
    {
      "target": "G8",
      "value": 144,
      "source": "Z4"
    },
    {
      "target": "Y5",
      "value": 141,
      "source": "P4"
    },
    {
      "target": "P4",
      "value": 139,
      "source": "P4"
    },
    {
      "target": "V2",
      "value": 132,
      "source": "I4"
    },
    {
      "target": "Z4",
      "value": 125,
      "source": "I4"
    },
    {
      "target": "Z4",
      "value": 125,
      "source": "H7"
    },
    {
      "target": "H4",
      "value": 123,
      "source": "V2"
    },
    {
      "target": "H4",
      "value": 122,
      "source": "I4"
    },
    {
      "target": "H4",
      "value": 121,
      "source": "H4"
    },
    {
      "target": "T4",
      "value": 120,
      "source": "H4"
    },
    {
      "target": "X2",
      "value": 120,
      "source": "H4"
    },
    {
      "target": "H7",
      "value": 118,
      "source": "X7"
    },
    {
      "target": "I4",
      "value": 115,
      "source": "Z4"
    },
    {
      "target": "G1",
      "value": 113,
      "source": "Y4"
    },
    {
      "target": "P4",
      "value": 112,
      "source": "A1"
    },
    {
      "target": "I4",
      "value": 108,
      "source": "P4"
    },
    {
      "target": "Z2",
      "value": 92,
      "source": "Z4"
    },
    {
      "target": "Z4",
      "value": 92,
      "source": "V2"
    },
    {
      "target": "P4",
      "value": 84,
      "source": "Z4"
    },
    {
      "target": "G1",
      "value": 83,
      "source": "G1"
    },
    {
      "target": "Z4",
      "value": 80,
      "source": "A3"
    },
    {
      "target": "I4",
      "value": 78,
      "source": "I1"
    },
    {
      "target": "G1",
      "value": 73,
      "source": "I1"
    },
    {
      "target": "G2",
      "value": 66,
      "source": "P4"
    },
    {
      "target": "H7",
      "value": 65,
      "source": "Y7"
    },
    {
      "target": "I4",
      "value": 52,
      "source": "G1"
    },
    {
      "target": "I2",
      "value": 52,
      "source": "I4"
    },
    {
      "target": "Z1",
      "value": 51,
      "source": "H4"
    },
    {
      "target": "G2",
      "value": 51,
      "source": "H4"
    },
    {
      "target": "X2",
      "value": 48,
      "source": "V2"
    },
    {
      "target": "Y4",
      "value": 47,
      "source": "A1"
    },
    {
      "target": "Z4",
      "value": 44,
      "source": "T5"
    },
    {
      "target": "Z1",
      "value": 43,
      "source": "P4"
    },
    {
      "target": "V2",
      "value": 42,
      "source": "Y4"
    },
    {
      "target": "S2",
      "value": 39,
      "source": "G2"
    },
    {
      "target": "Y4",
      "value": 39,
      "source": "P5"
    },
    {
      "target": "I4",
      "value": 38,
      "source": "A1"
    },
    {
      "target": "I6",
      "value": 35,
      "source": "I4"
    },
    {
      "target": "Y7",
      "value": 34,
      "source": "Z4"
    },
    {
      "target": "I4",
      "value": 33,
      "source": "V2"
    },
    {
      "target": "H4",
      "value": 32,
      "source": "W2"
    },
    {
      "target": "G3",
      "value": 32,
      "source": "Z1"
    },
    {
      "target": "P4",
      "value": 31,
      "source": "Y4"
    },
    {
      "target": "Z4",
      "value": 30,
      "source": "V3"
    },
    {
      "target": "I4",
      "value": 30,
      "source": "VL"
    },
    {
      "target": "V1",
      "value": 28,
      "source": "I1"
    },
    {
      "target": "G1",
      "value": 28,
      "source": "Z2"
    },
    {
      "target": "I3",
      "value": 28,
      "source": "G3"
    },
    {
      "target": "VL",
      "value": 27,
      "source": "Y4"
    },
    {
      "target": "H7",
      "value": 27,
      "source": "X2"
    },
    {
      "target": "Z2",
      "value": 26,
      "source": "Z2"
    },
    {
      "target": "Z4",
      "value": 26,
      "source": "T1"
    },
    {
      "target": "A1",
      "value": 25,
      "source": "Y4"
    },
    {
      "target": "H7",
      "value": 24,
      "source": "Y4"
    },
    {
      "target": "X7",
      "value": 24,
      "source": "H4"
    },
    {
      "target": "Z4",
      "value": 24,
      "source": "VL"
    },
    {
      "target": "G1",
      "value": 23,
      "source": "Z8"
    },
    {
      "target": "X2",
      "value": 23,
      "source": "VL"
    },
    {
      "target": "I4",
      "value": 23,
      "source": "Z2"
    },
    {
      "target": "Y4",
      "value": 23,
      "source": "I4"
    },
    {
      "target": "P5",
      "value": 22,
      "source": "H4"
    },
    {
      "target": "Y4",
      "value": 22,
      "source": "Y5"
    },
    {
      "target": "X2",
      "value": 20,
      "source": "Z4"
    },
    {
      "target": "G2",
      "value": 20,
      "source": "G2"
    },
    {
      "target": "Y5",
      "value": 19,
      "source": "X2"
    },
    {
      "target": "P5",
      "value": 19,
      "source": "P5"
    },
    {
      "target": "I7",
      "value": 19,
      "source": "I2"
    },
    {
      "target": "G3",
      "value": 19,
      "source": "I4"
    },
    {
      "target": "Y1",
      "value": 18,
      "source": "Y1"
    },
    {
      "target": "Z2",
      "value": 18,
      "source": "P4"
    },
    {
      "target": "P4",
      "value": 18,
      "source": "V2"
    },
    {
      "target": "T4",
      "value": 18,
      "source": "P4"
    },
    {
      "target": "G9",
      "value": 17,
      "source": "Z8"
    },
    {
      "target": "W2",
      "value": 17,
      "source": "P4"
    },
    {
      "target": "Z2",
      "value": 17,
      "source": "Y4"
    },
    {
      "target": "I1",
      "value": 17,
      "source": "V1"
    },
    {
      "target": "X2",
      "value": 17,
      "source": "P4"
    },
    {
      "target": "P5",
      "value": 16,
      "source": "Z4"
    },
    {
      "target": "G1",
      "value": 16,
      "source": "I4"
    },
    {
      "target": "X2",
      "value": 16,
      "source": "Y5"
    },
    {
      "target": "I4",
      "value": 15,
      "source": "Z1"
    },
    {
      "target": "I4",
      "value": 15,
      "source": "I5"
    },
    {
      "target": "Z4",
      "value": 15,
      "source": "Y4"
    },
    {
      "target": "I1",
      "value": 14,
      "source": "I1"
    },
    {
      "target": "I9",
      "value": 14,
      "source": "G9"
    },
    {
      "target": "G4",
      "value": 14,
      "source": "P4"
    },
    {
      "target": "H4",
      "value": 14,
      "source": "Z2"
    },
    {
      "target": "Z9",
      "value": 13,
      "source": "H7"
    },
    {
      "target": "G4",
      "value": 13,
      "source": "Z4"
    },
    {
      "target": "T2",
      "value": 13,
      "source": "G2"
    },
    {
      "target": "I1",
      "value": 11,
      "source": "I4"
    },
    {
      "target": "Z2",
      "value": 11,
      "source": "Z1"
    },
    {
      "target": "VL",
      "value": 11,
      "source": "I4"
    },
    {
      "target": "P4",
      "value": 10,
      "source": "I4"
    },
    {
      "target": "H4",
      "value": 10,
      "source": "Y5"
    },
    {
      "target": "H4",
      "value": 10,
      "source": "P4"
    },
    {
      "target": "S1",
      "value": 9,
      "source": "G1"
    },
    {
      "target": "G2",
      "value": 9,
      "source": "I2"
    },
    {
      "target": "H4",
      "value": 9,
      "source": "G2"
    },
    {
      "target": "Z2",
      "value": 9,
      "source": "G2"
    },
    {
      "target": "T4",
      "value": 8,
      "source": "Z4"
    },
    {
      "target": "I7",
      "value": 8,
      "source": "Y4"
    },
    {
      "target": "Z1",
      "value": 8,
      "source": "Y4"
    },
    {
      "target": "W2",
      "value": 8,
      "source": "Y4"
    },
    {
      "target": "Y5",
      "value": 7,
      "source": "Y5"
    },
    {
      "target": "I4",
      "value": 7,
      "source": "G3"
    },
    {
      "target": "G3",
      "value": 7,
      "source": "Y4"
    },
    {
      "target": "T3",
      "value": 7,
      "source": "G2"
    },
    {
      "target": "Z1",
      "value": 7,
      "source": "P5"
    },
    {
      "target": "V4",
      "value": 7,
      "source": "A1"
    },
    {
      "target": "W2",
      "value": 7,
      "source": "P5"
    },
    {
      "target": "H4",
      "value": 7,
      "source": "Z4"
    },
    {
      "target": "T4",
      "value": 6,
      "source": "H7"
    },
    {
      "target": "G2",
      "value": 6,
      "source": "T3"
    },
    {
      "target": "I2",
      "value": 6,
      "source": "Z2"
    },
    {
      "target": "T4",
      "value": 6,
      "source": "T2"
    },
    {
      "target": "Z1",
      "value": 6,
      "source": "Z1"
    },
    {
      "target": "I6",
      "value": 6,
      "source": "I6"
    },
    {
      "target": "A1",
      "value": 6,
      "source": "I2"
    },
    {
      "target": "G1",
      "value": 6,
      "source": "G8"
    },
    {
      "target": "G1",
      "value": 6,
      "source": "P4"
    },
    {
      "target": "X2",
      "value": 6,
      "source": "I4"
    },
    {
      "target": "G1",
      "value": 6,
      "source": "Z9"
    },
    {
      "target": "T1",
      "value": 6,
      "source": "G1"
    },
    {
      "target": "V2",
      "value": 5,
      "source": "H4"
    },
    {
      "target": "G2",
      "value": 5,
      "source": "G1"
    },
    {
      "target": "V5",
      "value": 5,
      "source": "I2"
    },
    {
      "target": "P5",
      "value": 5,
      "source": "V2"
    },
    {
      "target": "Z4",
      "value": 5,
      "source": "S1"
    },
    {
      "target": "I6",
      "value": 5,
      "source": "H4"
    },
    {
      "target": "A1",
      "value": 5,
      "source": "I4"
    },
    {
      "target": "P4",
      "value": 5,
      "source": "VL"
    },
    {
      "target": "Y4",
      "value": 5,
      "source": "Z2"
    },
    {
      "target": "Y4",
      "value": 5,
      "source": "X2"
    },
    {
      "target": "Y1",
      "value": 4,
      "source": "Z4"
    },
    {
      "target": "G2",
      "value": 4,
      "source": "I1"
    },
    {
      "target": "Y4",
      "value": 4,
      "source": "Z1"
    },
    {
      "target": "I7",
      "value": 4,
      "source": "W7"
    },
    {
      "target": "G2",
      "value": 4,
      "source": "W2"
    },
    {
      "target": "W2",
      "value": 4,
      "source": "Z4"
    },
    {
      "target": "I7",
      "value": 4,
      "source": "G1"
    },
    {
      "target": "H4",
      "value": 4,
      "source": "Y1"
    },
    {
      "target": "V3",
      "value": 4,
      "source": "H4"
    },
    {
      "target": "Z4",
      "value": 4,
      "source": "G3"
    },
    {
      "target": "Y5",
      "value": 4,
      "source": "I4"
    },
    {
      "target": "Z8",
      "value": 4,
      "source": "Z4"
    },
    {
      "target": "Y1",
      "value": 4,
      "source": "Y4"
    },
    {
      "target": "G3",
      "value": 4,
      "source": "Z4"
    },
    {
      "target": "P4",
      "value": 4,
      "source": "Z2"
    },
    {
      "target": "Z2",
      "value": 4,
      "source": "I4"
    },
    {
      "target": "G3",
      "value": 4,
      "source": "S1"
    },
    {
      "target": "Z2",
      "value": 4,
      "source": "V3"
    },
    {
      "target": "VL",
      "value": 4,
      "source": "X2"
    },
    {
      "target": "G9",
      "value": 4,
      "source": "Z9"
    },
    {
      "target": "G1",
      "value": 3,
      "source": "G2"
    },
    {
      "target": "X2",
      "value": 3,
      "source": "Y1"
    },
    {
      "target": "V3",
      "value": 3,
      "source": "I4"
    },
    {
      "target": "Z1",
      "value": 3,
      "source": "VL"
    },
    {
      "target": "Z4",
      "value": 3,
      "source": "G2"
    },
    {
      "target": "G2",
      "value": 3,
      "source": "Z9"
    },
    {
      "target": "I4",
      "value": 3,
      "source": "I6"
    },
    {
      "target": "X7",
      "value": 3,
      "source": "V2"
    },
    {
      "target": "X7",
      "value": 3,
      "source": "VL"
    },
    {
      "target": "I4",
      "value": 3,
      "source": "P5"
    },
    {
      "target": "Z4",
      "value": 3,
      "source": "I2"
    },
    {
      "target": "Z1",
      "value": 3,
      "source": "V2"
    },
    {
      "target": "Y4",
      "value": 3,
      "source": "V2"
    },
    {
      "target": "G3",
      "value": 3,
      "source": "P4"
    },
    {
      "target": "H7",
      "value": 3,
      "source": "V2"
    },
    {
      "target": "I7",
      "value": 2,
      "source": "H7"
    },
    {
      "target": "Z4",
      "value": 2,
      "source": "I1"
    },
    {
      "target": "A1",
      "value": 2,
      "source": "H4"
    },
    {
      "target": "W2",
      "value": 2,
      "source": "I4"
    },
    {
      "target": "P4",
      "value": 2,
      "source": "H7"
    },
    {
      "target": "X2",
      "value": 2,
      "source": "X2"
    },
    {
      "target": "T5",
      "value": 2,
      "source": "T5"
    },
    {
      "target": "P5",
      "value": 2,
      "source": "A1"
    },
    {
      "target": "I2",
      "value": 2,
      "source": "T2"
    },
    {
      "target": "P5",
      "value": 2,
      "source": "VL"
    },
    {
      "target": "W2",
      "value": 2,
      "source": "W2"
    },
    {
      "target": "Z4",
      "value": 2,
      "source": "V4"
    },
    {
      "target": "Y5",
      "value": 2,
      "source": "Y4"
    },
    {
      "target": "I1",
      "value": 2,
      "source": "Z1"
    },
    {
      "target": "G9",
      "value": 2,
      "source": "Z1"
    },
    {
      "target": "I2",
      "value": 2,
      "source": "G1"
    },
    {
      "target": "I2",
      "value": 2,
      "source": "T3"
    },
    {
      "target": "G1",
      "value": 2,
      "source": "I2"
    },
    {
      "target": "Z4",
      "value": 2,
      "source": "P5"
    },
    {
      "target": "P5",
      "value": 2,
      "source": "I4"
    },
    {
      "target": "I4",
      "value": 2,
      "source": "V3"
    },
    {
      "target": "Z8",
      "value": 2,
      "source": "H7"
    },
    {
      "target": "I3",
      "value": 2,
      "source": "I4"
    },
    {
      "target": "H4",
      "value": 2,
      "source": "Z1"
    },
    {
      "target": "Y7",
      "value": 2,
      "source": "P4"
    },
    {
      "target": "Y4",
      "value": 2,
      "source": "G2"
    },
    {
      "target": "X2",
      "value": 2,
      "source": "Y4"
    },
    {
      "target": "G3",
      "value": 2,
      "source": "H4"
    },
    {
      "target": "G3",
      "value": 2,
      "source": "S2"
    },
    {
      "target": "G1",
      "value": 1,
      "source": "I5"
    },
    {
      "target": "Z1",
      "value": 1,
      "source": "I4"
    },
    {
      "target": "X2",
      "value": 1,
      "source": "I6"
    },
    {
      "target": "V2",
      "value": 1,
      "source": "Y7"
    },
    {
      "target": "H4",
      "value": 1,
      "source": "H7"
    },
    {
      "target": "I7",
      "value": 1,
      "source": "I9"
    },
    {
      "target": "V3",
      "value": 1,
      "source": "V3"
    },
    {
      "target": "G9",
      "value": 1,
      "source": "P4"
    },
    {
      "target": "G2",
      "value": 1,
      "source": "Z8"
    },
    {
      "target": "T4",
      "value": 1,
      "source": "VL"
    },
    {
      "target": "I4",
      "value": 1,
      "source": "Y7"
    },
    {
      "target": "T2",
      "value": 1,
      "source": "I7"
    },
    {
      "target": "I7",
      "value": 1,
      "source": "X7"
    },
    {
      "target": "P4",
      "value": 1,
      "source": "T4"
    },
    {
      "target": "I7",
      "value": 1,
      "source": "Z4"
    },
    {
      "target": "Z9",
      "value": 1,
      "source": "Z4"
    },
    {
      "target": "Y4",
      "value": 1,
      "source": "S2"
    },
    {
      "target": "I2",
      "value": 1,
      "source": "V5"
    },
    {
      "target": "Y4",
      "value": 1,
      "source": "Y1"
    },
    {
      "target": "T3",
      "value": 1,
      "source": "G3"
    },
    {
      "target": "Y1",
      "value": 1,
      "source": "H7"
    },
    {
      "target": "V2",
      "value": 1,
      "source": "I7"
    },
    {
      "target": "H4",
      "value": 1,
      "source": "I1"
    },
    {
      "target": "P5",
      "value": 1,
      "source": "Z1"
    },
    {
      "target": "X7",
      "value": 1,
      "source": "H7"
    },
    {
      "target": "I5",
      "value": 1,
      "source": "I4"
    },
    {
      "target": "Z1",
      "value": 1,
      "source": "G1"
    },
    {
      "target": "A1",
      "value": 1,
      "source": "X2"
    },
    {
      "target": "V3",
      "value": 1,
      "source": "Y4"
    },
    {
      "target": "Z4",
      "value": 1,
      "source": "Z1"
    },
    {
      "target": "I6",
      "value": 1,
      "source": "X2"
    },
    {
      "target": "Z4",
      "value": 1,
      "source": "X7"
    },
    {
      "target": "H4",
      "value": 1,
      "source": "Y7"
    },
    {
      "target": "Z4",
      "value": 1,
      "source": "Z2"
    },
    {
      "target": "X2",
      "value": 1,
      "source": "Z2"
    },
    {
      "target": "VL",
      "value": 1,
      "source": "Z4"
    },
    {
      "target": "G4",
      "value": 1,
      "source": "Y4"
    },
    {
      "target": "I7",
      "value": 1,
      "source": "V3"
    },
    {
      "target": "I4",
      "value": 1,
      "source": "H7"
    },
    {
      "target": "H4",
      "value": 1,
      "source": "T4"
    },
    {
      "target": "W2",
      "value": 1,
      "source": "I2"
    },
    {
      "target": "T4",
      "value": 1,
      "source": "X2"
    },
    {
      "target": "W2",
      "value": 1,
      "source": "T4"
    },
    {
      "target": "Z1",
      "value": 1,
      "source": "I1"
    },
    {
      "target": "T2",
      "value": 1,
      "source": "T2"
    },
    {
      "target": "T1",
      "value": 1,
      "source": "V1"
    },
    {
      "target": "I7",
      "value": 1,
      "source": "I5"
    },
    {
      "target": "Y7",
      "value": 1,
      "source": "Y7"
    },
    {
      "target": "Y4",
      "value": 1,
      "source": "I1"
    },
    {
      "target": "H4",
      "value": 1,
      "source": "I6"
    },
    {
      "target": "I6",
      "value": 1,
      "source": "P4"
    },
    {
      "target": "G1",
      "value": 1,
      "source": "A1"
    },
    {
      "target": "A1",
      "value": 1,
      "source": "A3"
    },
    {
      "target": "I7",
      "value": 1,
      "source": "W2"
    },
    {
      "target": "V4",
      "value": 1,
      "source": "Z4"
    },
    {
      "target": "I4",
      "value": 1,
      "source": "G9"
    },
    {
      "target": "W7",
      "value": 1,
      "source": "Z4"
    },
    {
      "target": "I1",
      "value": 1,
      "source": "Z4"
    },
    {
      "target": "G2",
      "value": 1,
      "source": "Y7"
    },
    {
      "target": "P5",
      "value": 1,
      "source": "Y4"
    },
    {
      "target": "V2",
      "value": 1,
      "source": "I2"
    },
    {
      "target": "T3",
      "value": 1,
      "source": "I2"
    },
    {
      "target": "T2",
      "value": 1,
      "source": "Y4"
    },
    {
      "target": "P4",
      "value": 1,
      "source": "A3"
    },
    {
      "target": "I7",
      "value": 1,
      "source": "I4"
    },
    {
      "target": "X7",
      "value": 1,
      "source": "P4"
    },
    {
      "target": "Z8",
      "value": 1,
      "source": "H4"
    },
    {
      "target": "I7",
      "value": 1,
      "source": "V2"
    },
    {
      "target": "Z4",
      "value": 1,
      "source": "I5"
    },
    {
      "target": "X2",
      "value": 1,
      "source": "A1"
    },
    {
      "target": "W2",
      "value": 1,
      "source": "Z2"
    },
    {
      "target": "H7",
      "value": 1,
      "source": "Z4"
    },
    {
      "target": "V1",
      "value": 1,
      "source": "G1"
    },
    {
      "target": "W7",
      "value": 1,
      "source": "H7"
    },
    {
      "target": "Z4",
      "value": 1,
      "source": "I7"
    },
    {
      "target": "Z9",
      "value": 1,
      "source": "Z8"
    },
    {
      "target": "Y4",
      "value": 1,
      "source": "T4"
    },
    {
      "target": "Y1",
      "value": 1,
      "source": "P4"
    },
    {
      "target": "Z4",
      "value": 1,
      "source": "I3"
    },
    {
      "target": "W7",
      "value": 1,
      "source": "H4"
    },
    {
      "target": "I7",
      "value": 1,
      "source": "G9"
    },
    {
      "target": "I4",
      "value": 1,
      "source": "I3"
    },
    {
      "target": "Z2",
      "value": 1,
      "source": "G3"
    },
    {
      "target": "I2",
      "value": 1,
      "source": "Y4"
    },
    {
      "target": "Y4",
      "value": 1,
      "source": "I2"
    },
    {
      "target": "V3",
      "value": 1,
      "source": "Y7"
    },
    {
      "target": "P4",
      "value": 1,
      "source": "G4"
    },
    {
      "target": "I7",
      "value": 1,
      "source": "I1"
    },
    {
      "target": "T2",
      "value": 1,
      "source": "H4"
    },
    {
      "target": "Y7",
      "value": 1,
      "source": "G7"
    },
    {
      "target": "G1",
      "value": 1,
      "source": "W2"
    },
    {
      "target": "V2",
      "value": 1,
      "source": "V2"
    },
    {
      "target": "P5",
      "value": 1,
      "source": "P4"
    },
    {
      "target": "G3",
      "value": 1,
      "source": "X2"
    },
    {
      "target": "G3",
      "value": 1,
      "source": "G1"
    },
    {
      "target": "P4",
      "value": 1,
      "source": "W2"
    },
    {
      "target": "T1",
      "value": 1,
      "source": "G8"
    },
    {
      "target": "I7",
      "value": 1,
      "source": "I7"
    },
    {
      "target": "Y7",
      "value": 1,
      "source": "A1"
    },
    {
      "target": "I9",
      "value": 1,
      "source": "I7"
    },
    {
      "target": "P5",
      "value": 1,
      "source": "S2"
    },
    {
      "target": "I1",
      "value": 1,
      "source": "I2"
    },
    {
      "target": "Z2",
      "value": 1,
      "source": "I2"
    }
  ],
  "nodes": [
    {
      "group": 10,
      "id": "Y4"
    },
    {
      "group": 3,
      "id": "I4"
    },
    {
      "group": 3,
      "id": "I3"
    },
    {
      "group": 4,
      "id": "P5"
    },
    {
      "group": 0,
      "id": "A3"
    },
    {
      "group": 11,
      "id": "Z4"
    },
    {
      "group": 4,
      "id": "P4"
    },
    {
      "group": 7,
      "id": "V4"
    },
    {
      "group": 2,
      "id": "H4"
    },
    {
      "group": 8,
      "id": "W2"
    },
    {
      "group": 11,
      "id": "Z2"
    },
    {
      "group": 3,
      "id": "I2"
    },
    {
      "group": 6,
      "id": "T2"
    },
    {
      "group": 0,
      "id": "A1"
    },
    {
      "group": 7,
      "id": "V2"
    },
    {
      "group": 3,
      "id": "I7"
    },
    {
      "group": 0,
      "id": "A2"
    },
    {
      "group": 1,
      "id": "G2"
    },
    {
      "group": 6,
      "id": "T5"
    },
    {
      "group": 9,
      "id": "X2"
    },
    {
      "group": 7,
      "id": "VL"
    },
    {
      "group": 2,
      "id": "H7"
    },
    {
      "group": 11,
      "id": "Z1"
    },
    {
      "group": 1,
      "id": "G1"
    },
    {
      "group": 3,
      "id": "I1"
    },
    {
      "group": 10,
      "id": "Y7"
    },
    {
      "group": 7,
      "id": "V3"
    },
    {
      "group": 6,
      "id": "T4"
    },
    {
      "group": 5,
      "id": "S2"
    },
    {
      "group": 1,
      "id": "G3"
    },
    {
      "group": 3,
      "id": "I5"
    },
    {
      "group": 6,
      "id": "T1"
    },
    {
      "group": 11,
      "id": "Z8"
    },
    {
      "group": 1,
      "id": "G8"
    },
    {
      "group": 10,
      "id": "Y1"
    },
    {
      "group": 1,
      "id": "G9"
    },
    {
      "group": 9,
      "id": "X7"
    },
    {
      "group": 1,
      "id": "G4"
    },
    {
      "group": 3,
      "id": "I9"
    },
    {
      "group": 7,
      "id": "V1"
    },
    {
      "group": 5,
      "id": "S1"
    },
    {
      "group": 10,
      "id": "Y5"
    },
    {
      "group": 3,
      "id": "I6"
    },
    {
      "group": 3,
      "id": "I8"
    },
    {
      "group": 11,
      "id": "Z9"
    },
    {
      "group": 6,
      "id": "T3"
    },
    {
      "group": 7,
      "id": "V5"
    },
    {
      "group": 8,
      "id": "W7"
    },
    {
      "group": 1,
      "id": "G7"
    },
    {
      "group": 1,
      "id": "G5"
    }
  ]
}